pyvoices/__init__.py
pyvoices/__main__.py
pyvoices/doculect.py
pyvoices/commands/__init__.py
pyvoices/commands/chunk.py
pyvoices-0.2.0.dist-info/LICENSE
pyvoices-0.2.0.dist-info/METADATA
pyvoices-0.2.0.dist-info/WHEEL
pyvoices-0.2.0.dist-info/entry_points.txt
pyvoices-0.2.0.dist-info/top_level.txt
pyvoices-0.2.0.dist-info/RECORD
