Metadata-Version: 2.1
Name: pyvoices
Version: 0.2.0
Summary: Python library to curate "* Voices" data
Home-page: https://github.com/dlce-eva/pyvoices
Author: Robert Forkel and Hans-Jörg Bibiko
Author-email: dlce.rdm@eva.mpg.de
License: Apache 2.0
Platform: any
Classifier: Development Status :: 5 - Production/Stable
Classifier: Intended Audience :: Developers
Classifier: Intended Audience :: Science/Research
Classifier: Natural Language :: English
Classifier: Operating System :: OS Independent
Classifier: Programming Language :: Python :: 3
Classifier: Programming Language :: Python :: 3.8
Classifier: Programming Language :: Python :: 3.9
Classifier: Programming Language :: Python :: 3.10
Classifier: Programming Language :: Python :: 3.11
Classifier: Programming Language :: Python :: Implementation :: CPython
Classifier: Programming Language :: Python :: Implementation :: PyPy
Classifier: License :: OSI Approved :: Apache Software License
Requires-Python: >=3.8
License-File: LICENSE
Requires-Dist: csvw (>=3.1.3)
Requires-Dist: cldfcatalog (>=1.5.1)
Requires-Dist: clldutils (>=3.20.0)
Requires-Dist: pycldf (>=1.28.0)
Requires-Dist: openpyxl (>=3.1.2)
Requires-Dist: pydub (>=0.25.1)
Requires-Dist: praatio (>=6.0.1)
Requires-Dist: pympi-ling (>=1.70.2)
Provides-Extra: dev
Requires-Dist: build ; extra == 'dev'
Requires-Dist: tox ; extra == 'dev'
Requires-Dist: flake8 ; extra == 'dev'
Requires-Dist: wheel (>=0.36) ; extra == 'dev'
Requires-Dist: twine ; extra == 'dev'
Provides-Extra: test
Requires-Dist: pytest (>=7) ; extra == 'test'
Requires-Dist: pytest-mock ; extra == 'test'
Requires-Dist: pytest-cov ; extra == 'test'
Requires-Dist: coverage (>=7) ; extra == 'test'
